gtrace/__init__.py
gtrace/beam.py
gtrace/nonsequential.py
gtrace/optcomp.py
gtrace/unit.py
gtrace/draw/__init__.py
gtrace/draw/draw.py
gtrace/draw/dxf.py
gtrace/draw/renderer.py
gtrace/draw/tools.py
gtrace/optics/__init__.py
gtrace/optics/cavity.py
gtrace/optics/consts.py
gtrace/optics/gaussian.py
gtrace/optics/geometric.py
gtrace/optics/unit.py
gtrace-0.2.4.dist-info/LICENSE
gtrace-0.2.4.dist-info/METADATA
gtrace-0.2.4.dist-info/WHEEL
gtrace-0.2.4.dist-info/top_level.txt
gtrace-0.2.4.dist-info/RECORD
